{"cameraMode":{"drawMode":0,"name":"Shaded","section":"Shading Mode"},"sceneLighting":true,"audioPlay":false,"sceneViewState":{"m_AlwaysRefresh":false,"showFog":true,"showSkybox":true,"showFlares":true,"showImageEffects":true,"showParticleSystems":true,"showVisualEffectGraphs":true,"m_FxEnabled":true},"in2DMode":false,"pivot":{"x":0.0,"y":0.0,"z":12.5},"rotation":{"x":-0.16747312247753144,"y":0.4753125309944153,"z":-0.09215626865625382,"w":-0.858974039554596},"size":21.81462287902832,"orthographic":false}